xarray_compare/__init__.py
xarray_compare/compare.py
xarray_compare/utils.py
xarray_compare-0.2.0.dist-info/LICENSE
xarray_compare-0.2.0.dist-info/WHEEL
xarray_compare-0.2.0.dist-info/METADATA
xarray_compare-0.2.0.dist-info/RECORD
